aicapi_yw3760/__init__.py
aicapi_yw3760/aicapi_yw3760.py
aicapi_yw3760-0.1.2.dist-info/LICENSE
aicapi_yw3760-0.1.2.dist-info/WHEEL
aicapi_yw3760-0.1.2.dist-info/METADATA
aicapi_yw3760-0.1.2.dist-info/RECORD
