Metadata-Version: 2.1
Name: aicapi-yw3760
Version: 0.1.2
Summary: This is a python package of an API CLIENT to retrieve the data of collections in the Atr Institute of Chicago.
Home-page: https://github.com/nicolewang97/AICAPI_YW3760
License: MIT
Author: yw3760
Requires-Python: >=3.9,<4.0
Classifier: License :: OSI Approved :: MIT License
Classifier: Programming Language :: Python :: 3
Classifier: Programming Language :: Python :: 3.10
Classifier: Programming Language :: Python :: 3.9
Requires-Dist: Pillow (>=8.4.0,<9.0.0)
Requires-Dist: ipython (>=7.30.1,<8.0.0)
Requires-Dist: pandas (>=1.3.5,<2.0.0)
Project-URL: Documentation, https://aicapi-yw3760.readthedocs.io
Project-URL: Repository, https://github.com/nicolewang97/AICAPI_YW3760
